README.md
setup.py
mnmetro/__init__.py
mnmetro/main.py
mnmetro.egg-info/PKG-INFO
mnmetro.egg-info/SOURCES.txt
mnmetro.egg-info/dependency_links.txt
mnmetro.egg-info/requires.txt
mnmetro.egg-info/top_level.txt