Metadata-Version: 2.1
Name: mnmetro
Version: 1.0.0
Summary: A wrapper for the Minnesota Metro API
Home-page: https://github.com/trjahnke/mnmetro
Author: Tristan Jahnke
Author-email: trjahnke@gmail.com
License: UNKNOWN
Platform: UNKNOWN
Classifier: Programming Language :: Python :: 3.6
Classifier: License :: OSI Approved :: GNU General Public License v3 (GPLv3)
Classifier: Operating System :: OS Independent
Classifier: Natural Language :: English
Classifier: Development Status :: 5 - Production/Stable
Requires-Python: >=3.6
